pyClark/LICENSE
pyClark/__init__.py
pyClark/clark.py
pyClark/utils.py
pyClark-0.0.1.data/data/LICENSE
pyClark-0.0.1.dist-info/METADATA
pyClark-0.0.1.dist-info/RECORD
pyClark-0.0.1.dist-info/WHEEL
pyClark-0.0.1.dist-info/top_level.txt
