Metadata-Version: 2.1
Name: pyClark
Version: 0.0.1
Summary: Remote error reporting that helps save the day
Home-page: https://github.com/Podshot/pyClark
Author: Podshot
Author-email: ben.gothard3@gmail.com
License: GNU LGPLv3
Keywords: development
Platform: UNKNOWN
Classifier: Development Status :: 2 - Pre-Alpha
Classifier: Intended Audience :: Developers
Classifier: Topic :: Software Development :: Bug Tracking
Classifier: Topic :: System :: Monitoring
Classifier: Programming Language :: Python :: 2.7
Classifier: Programming Language :: Python :: 3.6
Requires-Dist: requests
